puprelease/__init__.py
puprelease/check.py
puprelease/pup.py
puprelease/release.py
puprelease/util.py
puprelease-1.8.2.dist-info/LICENSE
puprelease-1.8.2.dist-info/METADATA
puprelease-1.8.2.dist-info/WHEEL
puprelease-1.8.2.dist-info/entry_points.txt
puprelease-1.8.2.dist-info/top_level.txt
puprelease-1.8.2.dist-info/RECORD
