Metadata-Version: 2.1
Name: puprelease
Version: 1.8.2
Summary: Publishing a new version of your Python package has never been easier
Home-page: https://github.com/tfiers/puprelease
Author: Tomas Fiers
Author-email: tomas.fiers@gmail.com
License: UNKNOWN
Project-URL: Source Code, https://github.com/tfiers/puprelease
Platform: UNKNOWN
Classifier: License :: OSI Approved :: MIT License
Classifier: Programming Language :: Python :: 3
Classifier: Operating System :: OS Independent
License-File: LICENSE
Requires-Dist: click (>=7.1)
Requires-Dist: requests (~=2.0)
Requires-Dist: twine
Requires-Dist: wheel
Requires-Dist: setuptools-scm
Requires-Dist: colorama ; platform_system == "Windows"
